igeAppsFlyer.cp37-win32.pyd
igeAppsFlyer-0.0.2.dist-info/LICENSE
igeAppsFlyer-0.0.2.dist-info/METADATA
igeAppsFlyer-0.0.2.dist-info/WHEEL
igeAppsFlyer-0.0.2.dist-info/top_level.txt
igeAppsFlyer-0.0.2.dist-info/RECORD
